Metadata-Version: 2.1
Name: goja-py
Version: 0.1.0
Summary: Goja ECMAScript 5.1 runtime for Python
Author-email: Dmitriy Makeev <makeev.dimitry@gmail.com>
License: MIT License
Project-URL: Source, https://github.com/DmitriyMakeev/goja-py
Keywords: python3,goja,javascript,runtime
Classifier: License :: OSI Approved :: MIT License
Classifier: Programming Language :: Python
Classifier: Programming Language :: Python :: 3
Requires-Python: >=3.10
License-File: LICENSE
